pypef/__init__.py
pypef/main.py
pypef/settings.py
pypef/dca/__init__.py
pypef/dca/gremlin_inference.py
pypef/dca/plmc_encoding.py
pypef/gui/qt_window.py
pypef/hybrid/__init__.py
pypef/hybrid/hybrid_model.py
pypef/hybrid/hybrid_run.py
pypef/llm/__init__.py
pypef/llm/esm_lora_tune.py
pypef/llm/inference.py
pypef/llm/prosst_lora_tune.py
pypef/llm/utils.py
pypef/llm/prosst_structure/__init__.py
pypef/llm/prosst_structure/quantizer.py
pypef/llm/prosst_structure/scatter.py
pypef/llm/prosst_structure/encoder/__init__.py
pypef/llm/prosst_structure/encoder/gvp.py
pypef/llm/prosst_structure/encoder/layer.py
pypef/llm/prosst_structure/static/2048_kmeans_cluster_centers.npy
pypef/llm/prosst_structure/static/AE.pt
pypef/llm/prosst_structure/static/AE_CPU.pt
pypef/ml/__init__.py
pypef/ml/ml_run.py
pypef/ml/parallelization.py
pypef/ml/regression.py
pypef/ml/AAindex/ANDN920101.txt
pypef/ml/AAindex/ARGP820101.txt
pypef/ml/AAindex/ARGP820102.txt
pypef/ml/AAindex/ARGP820103.txt
pypef/ml/AAindex/AURR980101.txt
pypef/ml/AAindex/AURR980102.txt
pypef/ml/AAindex/AURR980103.txt
pypef/ml/AAindex/AURR980104.txt
pypef/ml/AAindex/AURR980105.txt
pypef/ml/AAindex/AURR980106.txt
pypef/ml/AAindex/AURR980107.txt
pypef/ml/AAindex/AURR980108.txt
pypef/ml/AAindex/AURR980109.txt
pypef/ml/AAindex/AURR980110.txt
pypef/ml/AAindex/AURR980111.txt
pypef/ml/AAindex/AURR980112.txt
pypef/ml/AAindex/AURR980113.txt
pypef/ml/AAindex/AURR980114.txt
pypef/ml/AAindex/AURR980115.txt
pypef/ml/AAindex/AURR980116.txt
pypef/ml/AAindex/AURR980117.txt
pypef/ml/AAindex/AURR980118.txt
pypef/ml/AAindex/AURR980119.txt
pypef/ml/AAindex/AURR980120.txt
pypef/ml/AAindex/AVBF000101.txt
pypef/ml/AAindex/AVBF000102.txt
pypef/ml/AAindex/AVBF000103.txt
pypef/ml/AAindex/AVBF000104.txt
pypef/ml/AAindex/AVBF000105.txt
pypef/ml/AAindex/AVBF000106.txt
pypef/ml/AAindex/AVBF000107.txt
pypef/ml/AAindex/AVBF000108.txt
pypef/ml/AAindex/AVBF000109.txt
pypef/ml/AAindex/BAEK050101.txt
pypef/ml/AAindex/BASU050101.txt
pypef/ml/AAindex/BASU050102.txt
pypef-0.4.3.dist-info/licenses/LICENSE.md
pypef-0.4.3.dist-info/METADATA
pypef-0.4.3.dist-info/WHEEL
pypef-0.4.3.dist-info/entry_points.txt
pypef-0.4.3.dist-info/top_level.txt
pypef-0.4.3.dist-info/RECORD
