Metadata-Version: 2.4
Name: pypef
Version: 0.4.3
Summary: A tool for performing data-driven protein engineering by building machine learning models from protein variant fitness data.
Author: Alexander-Maurice Illig
Author-email: Niklas Siedhoff <niklas.siedhoff@rwth-aachen.de>
License: CC BY-SA 4.0
Project-URL: Homepage, https://github.com/niklases/PyPEF
Keywords: Pythonic Protein Engineering Framework
Classifier: Development Status :: 3 - Alpha
Classifier: Programming Language :: Python :: 3
Classifier: Programming Language :: Python :: 3.10
Classifier: Programming Language :: Python :: 3.11
Classifier: Programming Language :: Python :: 3.12
Classifier: Programming Language :: Python :: 3.13
Classifier: Topic :: Scientific/Engineering :: Bio-Informatics
Classifier: Topic :: Scientific/Engineering :: Artificial Intelligence
Requires-Python: >=3.10
License-File: LICENSE.md
Requires-Dist: numpy
Requires-Dist: pandas
Requires-Dist: tqdm
Requires-Dist: docopt-ng
Requires-Dist: matplotlib
Requires-Dist: scipy
Requires-Dist: adjustText
Requires-Dist: scikit-learn
Requires-Dist: biopython
Requires-Dist: biotite
Requires-Dist: schema
Requires-Dist: pathos
Requires-Dist: peft
Requires-Dist: pynvml
Requires-Dist: torch
Requires-Dist: torch-geometric
Provides-Extra: gui
Requires-Dist: pyside6; extra == "gui"
Dynamic: license-file
